warc_extractor/__init__.py
warc_extractor/warc_extractor.py
warc_extractor-0.1.1.dist-info/entry_points.txt
warc_extractor-0.1.1.dist-info/LICENSE
warc_extractor-0.1.1.dist-info/WHEEL
warc_extractor-0.1.1.dist-info/METADATA
warc_extractor-0.1.1.dist-info/RECORD
